{"Ranked Duel 1v1": {"Ranks": [{"Rank": "Supersonic Legend", "Players": "1_062", "Player_Percentage": "0.09", "Divisions": {"Division I": {"lower_bound": "1_356", "upper_bound": "1_528"}}}, {"Rank": "Grand Champion III", "Players": "1_365", "Player_Percentage": "0.12", "Divisions": {"Division I": {"lower_bound": "1_290", "upper_bound": "1_298"}, "Division II": {"lower_bound": "1_299", "upper_bound": "1_315"}, "Division III": {"lower_bound": "1_318", "upper_bound": "1_333"}, "Division IV": {"lower_bound": "1_338", "upper_bound": "1_353"}}}, {"Rank": "Grand Champion II", "Players": "1_724", "Player_Percentage": "0.15", "Divisions": {"Division I": {"lower_bound": "1_235", "upper_bound": "1_238"}, "Division II": {"lower_bound": "1_241", "upper_bound": "1_256"}, "Division III": {"lower_bound": "1_258", "upper_bound": "1_275"}, "Division IV": {"lower_bound": "1_277", "upper_bound": "1_294"}}}, {"Rank": "Grand Champion I", "Players": "3_128", "Player_Percentage": "0.27", "Divisions": {"Division I": {"lower_bound": "1_175", "upper_bound": "1_178"}, "Division II": {"lower_bound": "1_180", "upper_bound": "1_196"}, "Division III": {"lower_bound": "1_198", "upper_bound": "1_215"}, "Division IV": {"lower_bound": "1_217", "upper_bound": "1_234"}}}, {"Rank": "Champion III", "Players": "6_035", "Player_Percentage": "0.52", "Divisions": {"Division I": {"lower_bound": "1_115", "upper_bound": "1_118"}, "Division II": {"lower_bound": "1_121", "upper_bound": "1_136"}, "Division III": {"lower_bound": "1_138", "upper_bound": "1_147"}, "Division IV": {"lower_bound": "1_157", "upper_bound": "1_172"}}}, {"Rank": "Champion II", "Players": "11_200", "Player_Percentage": "0.96", "Divisions": {"Division I": {"lower_bound": "1_055", "upper_bound": "1_058"}, "Division II": {"lower_bound": "1_060", "upper_bound": "1_077"}, "Division III": {"lower_bound": "1_078", "upper_bound": "1_094"}, "Division IV": {"lower_bound": "1_097", "upper_bound": "1_112"}}}, {"Rank": "Champion I", "Players": "20_852", "Player_Percentage": "1.79", "Divisions": {"Division I": {"lower_bound": "995", "upper_bound": "998"}, "Division II": {"lower_bound": "1_000", "upper_bound": "1_007"}, "Division III": {"lower_bound": "1_018", "upper_bound": "1_028"}, "Division IV": {"lower_bound": "1_037", "upper_bound": "1_050"}}}, {"Rank": "Diamond III", "Players": "39_219", "Player_Percentage": "3.36", "Divisions": {"Division I": {"lower_bound": "935", "upper_bound": "938"}, "Division II": {"lower_bound": "940", "upper_bound": "957"}, "Division III": {"lower_bound": "958", "upper_bound": "973"}, "Division IV": {"lower_bound": "977", "upper_bound": "993"}}}, {"Rank": "Diamond II", "Players": "63_298", "Player_Percentage": "5.42", "Divisions": {"Division I": {"lower_bound": "875", "upper_bound": "878"}, "Division II": {"lower_bound": "880", "upper_bound": "893"}, "Division III": {"lower_bound": "898", "upper_bound": "909"}, "Division IV": {"lower_bound": "917", "upper_bound": "931"}}}, {"Rank": "Diamond I", "Players": "98_616", "Player_Percentage": "8.45", "Divisions": {"Division I": {"lower_bound": "815", "upper_bound": "818"}, "Division II": {"lower_bound": "820", "upper_bound": "837"}, "Division III": {"lower_bound": "838", "upper_bound": "855"}, "Division IV": {"lower_bound": "857", "upper_bound": "874"}}}, {"Rank": "Platinum III", "Players": "136_851", "Player_Percentage": "11.73", "Divisions": {"Division I": {"lower_bound": "755", "upper_bound": "758"}, "Division II": {"lower_bound": "759", "upper_bound": "777"}, "Division III": {"lower_bound": "778", "upper_bound": "793"}, "Division IV": {"lower_bound": "797", "upper_bound": "810"}}}, {"Rank": "Platinum II", "Players": "162_222", "Player_Percentage": "13.90", "Divisions": {"Division I": {"lower_bound": "695", "upper_bound": "698"}, "Division II": {"lower_bound": "699", "upper_bound": "717"}, "Division III": {"lower_bound": "718", "upper_bound": "735"}, "Division IV": {"lower_bound": "737", "upper_bound": "754"}}}, {"Rank": "Platinum I", "Players": "166_646", "Player_Percentage": "14.28", "Divisions": {"Division I": {"lower_bound": "635", "upper_bound": "638"}, "Division II": {"lower_bound": "639", "upper_bound": "657"}, "Division III": {"lower_bound": "658", "upper_bound": "676"}, "Division IV": {"lower_bound": "677", "upper_bound": "694"}}}, {"Rank": "Gold III", "Players": "131_022", "Player_Percentage": "11.23", "Divisions": {"Division I": {"lower_bound": "575", "upper_bound": "578"}, "Division II": {"lower_bound": "580", "upper_bound": "597"}, "Division III": {"lower_bound": "598", "upper_bound": "615"}, "Division IV": {"lower_bound": "617", "upper_bound": "634"}}}, {"Rank": "Gold II", "Players": "92_427", "Player_Percentage": "7.92", "Divisions": {"Division I": {"lower_bound": "515", "upper_bound": "518"}, "Division II": {"lower_bound": "520", "upper_bound": "537"}, "Division III": {"lower_bound": "538", "upper_bound": "556"}, "Division IV": {"lower_bound": "557", "upper_bound": "574"}}}, {"Rank": "Gold I", "Players": "56_654", "Player_Percentage": "4.85", "Divisions": {"Division I": {"lower_bound": "455", "upper_bound": "458"}, "Division II": {"lower_bound": "460", "upper_bound": "477"}, "Division III": {"lower_bound": "478", "upper_bound": "495"}, "Division IV": {"lower_bound": "497", "upper_bound": "514"}}}, {"Rank": "Silver III", "Players": "29_468", "Player_Percentage": "2.52", "Divisions": {"Division I": {"lower_bound": "395", "upper_bound": "398"}, "Division II": {"lower_bound": "400", "upper_bound": "417"}, "Division III": {"lower_bound": "423", "upper_bound": "435"}, "Division IV": {"lower_bound": "437", "upper_bound": "454"}}}, {"Rank": "Silver II", "Players": "14_517", "Player_Percentage": "1.24", "Divisions": {"Division I": {"lower_bound": "335", "upper_bound": "338"}, "Division II": {"lower_bound": "344", "upper_bound": "357"}, "Division III": {"lower_bound": "364", "upper_bound": "375"}, "Division IV": {"lower_bound": "377", "upper_bound": "394"}}}, {"Rank": "Silver I", "Players": "6_357", "Player_Percentage": "0.54", "Divisions": {"Division I": {"lower_bound": "275", "upper_bound": "278"}, "Division II": {"lower_bound": "280", "upper_bound": "297"}, "Division III": {"lower_bound": "301", "upper_bound": "315"}, "Division IV": {"lower_bound": "317", "upper_bound": "334"}}}, {"Rank": "Bronze III", "Players": "2_617", "Player_Percentage": "0.22", "Divisions": {"Division I": {"lower_bound": "215", "upper_bound": "218"}, "Division II": {"lower_bound": "221", "upper_bound": "237"}, "Division III": {"lower_bound": "240", "upper_bound": "255"}, "Division IV": {"lower_bound": "263", "upper_bound": "274"}}}, {"Rank": "Bronze II", "Players": "1_065", "Player_Percentage": "0.09", "Divisions": {"Division I": {"lower_bound": "155", "upper_bound": "158"}, "Division II": {"lower_bound": "164", "upper_bound": "177"}, "Division III": {"lower_bound": "183", "upper_bound": "195"}, "Division IV": {"lower_bound": "199", "upper_bound": "213"}}}, {"Rank": "Bronze I", "Players": "407", "Player_Percentage": "0.03", "Divisions": {"Division II": {"lower_bound": "126", "upper_bound": "126"}, "Division III": {"lower_bound": "129", "upper_bound": "134"}, "Division IV": {"lower_bound": "144", "upper_bound": "152"}}}, {"Rank": "Unranked", "Players": "120_375", "Player_Percentage": "10.31", "Divisions": {"Division I": {"lower_bound": "504", "upper_bound": "774"}}}]}, "Ranked Doubles 2v2": {"Ranks": [{"Rank": "Supersonic Legend", "Players": "1_062", "Player_Percentage": "0.09", "Divisions": {"Division I": {"lower_bound": "1_356", "upper_bound": "1_528"}}}, {"Rank": "Grand Champion III", "Players": "1_365", "Player_Percentage": "0.12", "Divisions": {"Division I": {"lower_bound": "1_290", "upper_bound": "1_298"}, "Division II": {"lower_bound": "1_299", "upper_bound": "1_315"}, "Division III": {"lower_bound": "1_318", "upper_bound": "1_333"}, "Division IV": {"lower_bound": "1_338", "upper_bound": "1_353"}}}, {"Rank": "Grand Champion II", "Players": "1_724", "Player_Percentage": "0.15", "Divisions": {"Division I": {"lower_bound": "1_235", "upper_bound": "1_238"}, "Division II": {"lower_bound": "1_241", "upper_bound": "1_256"}, "Division III": {"lower_bound": "1_258", "upper_bound": "1_275"}, "Division IV": {"lower_bound": "1_277", "upper_bound": "1_294"}}}, {"Rank": "Grand Champion I", "Players": "3_128", "Player_Percentage": "0.27", "Divisions": {"Division I": {"lower_bound": "1_175", "upper_bound": "1_178"}, "Division II": {"lower_bound": "1_180", "upper_bound": "1_196"}, "Division III": {"lower_bound": "1_198", "upper_bound": "1_215"}, "Division IV": {"lower_bound": "1_217", "upper_bound": "1_234"}}}, {"Rank": "Champion III", "Players": "6_035", "Player_Percentage": "0.52", "Divisions": {"Division I": {"lower_bound": "1_115", "upper_bound": "1_118"}, "Division II": {"lower_bound": "1_121", "upper_bound": "1_136"}, "Division III": {"lower_bound": "1_138", "upper_bound": "1_147"}, "Division IV": {"lower_bound": "1_157", "upper_bound": "1_172"}}}, {"Rank": "Champion II", "Players": "11_200", "Player_Percentage": "0.96", "Divisions": {"Division I": {"lower_bound": "1_055", "upper_bound": "1_058"}, "Division II": {"lower_bound": "1_060", "upper_bound": "1_077"}, "Division III": {"lower_bound": "1_078", "upper_bound": "1_094"}, "Division IV": {"lower_bound": "1_097", "upper_bound": "1_112"}}}, {"Rank": "Champion I", "Players": "20_852", "Player_Percentage": "1.79", "Divisions": {"Division I": {"lower_bound": "995", "upper_bound": "998"}, "Division II": {"lower_bound": "1_000", "upper_bound": "1_007"}, "Division III": {"lower_bound": "1_018", "upper_bound": "1_028"}, "Division IV": {"lower_bound": "1_037", "upper_bound": "1_050"}}}, {"Rank": "Diamond III", "Players": "39_219", "Player_Percentage": "3.36", "Divisions": {"Division I": {"lower_bound": "935", "upper_bound": "938"}, "Division II": {"lower_bound": "940", "upper_bound": "957"}, "Division III": {"lower_bound": "958", "upper_bound": "973"}, "Division IV": {"lower_bound": "977", "upper_bound": "993"}}}, {"Rank": "Diamond II", "Players": "63_298", "Player_Percentage": "5.42", "Divisions": {"Division I": {"lower_bound": "875", "upper_bound": "878"}, "Division II": {"lower_bound": "880", "upper_bound": "893"}, "Division III": {"lower_bound": "898", "upper_bound": "909"}, "Division IV": {"lower_bound": "917", "upper_bound": "931"}}}, {"Rank": "Diamond I", "Players": "98_616", "Player_Percentage": "8.45", "Divisions": {"Division I": {"lower_bound": "815", "upper_bound": "818"}, "Division II": {"lower_bound": "820", "upper_bound": "837"}, "Division III": {"lower_bound": "838", "upper_bound": "855"}, "Division IV": {"lower_bound": "857", "upper_bound": "874"}}}, {"Rank": "Platinum III", "Players": "136_851", "Player_Percentage": "11.73", "Divisions": {"Division I": {"lower_bound": "755", "upper_bound": "758"}, "Division II": {"lower_bound": "759", "upper_bound": "777"}, "Division III": {"lower_bound": "778", "upper_bound": "793"}, "Division IV": {"lower_bound": "797", "upper_bound": "810"}}}, {"Rank": "Platinum II", "Players": "162_222", "Player_Percentage": "13.90", "Divisions": {"Division I": {"lower_bound": "695", "upper_bound": "698"}, "Division II": {"lower_bound": "699", "upper_bound": "717"}, "Division III": {"lower_bound": "718", "upper_bound": "735"}, "Division IV": {"lower_bound": "737", "upper_bound": "754"}}}, {"Rank": "Platinum I", "Players": "166_646", "Player_Percentage": "14.28", "Divisions": {"Division I": {"lower_bound": "635", "upper_bound": "638"}, "Division II": {"lower_bound": "639", "upper_bound": "657"}, "Division III": {"lower_bound": "658", "upper_bound": "676"}, "Division IV": {"lower_bound": "677", "upper_bound": "694"}}}, {"Rank": "Gold III", "Players": "131_022", "Player_Percentage": "11.23", "Divisions": {"Division I": {"lower_bound": "575", "upper_bound": "578"}, "Division II": {"lower_bound": "580", "upper_bound": "597"}, "Division III": {"lower_bound": "598", "upper_bound": "615"}, "Division IV": {"lower_bound": "617", "upper_bound": "634"}}}, {"Rank": "Gold II", "Players": "92_427", "Player_Percentage": "7.92", "Divisions": {"Division I": {"lower_bound": "515", "upper_bound": "518"}, "Division II": {"lower_bound": "520", "upper_bound": "537"}, "Division III": {"lower_bound": "538", "upper_bound": "556"}, "Division IV": {"lower_bound": "557", "upper_bound": "574"}}}, {"Rank": "Gold I", "Players": "56_654", "Player_Percentage": "4.85", "Divisions": {"Division I": {"lower_bound": "455", "upper_bound": "458"}, "Division II": {"lower_bound": "460", "upper_bound": "477"}, "Division III": {"lower_bound": "478", "upper_bound": "495"}, "Division IV": {"lower_bound": "497", "upper_bound": "514"}}}, {"Rank": "Silver III", "Players": "29_468", "Player_Percentage": "2.52", "Divisions": {"Division I": {"lower_bound": "395", "upper_bound": "398"}, "Division II": {"lower_bound": "400", "upper_bound": "417"}, "Division III": {"lower_bound": "423", "upper_bound": "435"}, "Division IV": {"lower_bound": "437", "upper_bound": "454"}}}, {"Rank": "Silver II", "Players": "14_517", "Player_Percentage": "1.24", "Divisions": {"Division I": {"lower_bound": "335", "upper_bound": "338"}, "Division II": {"lower_bound": "344", "upper_bound": "357"}, "Division III": {"lower_bound": "364", "upper_bound": "375"}, "Division IV": {"lower_bound": "377", "upper_bound": "394"}}}, {"Rank": "Silver I", "Players": "6_357", "Player_Percentage": "0.54", "Divisions": {"Division I": {"lower_bound": "275", "upper_bound": "278"}, "Division II": {"lower_bound": "280", "upper_bound": "297"}, "Division III": {"lower_bound": "301", "upper_bound": "315"}, "Division IV": {"lower_bound": "317", "upper_bound": "334"}}}, {"Rank": "Bronze III", "Players": "2_617", "Player_Percentage": "0.22", "Divisions": {"Division I": {"lower_bound": "215", "upper_bound": "218"}, "Division II": {"lower_bound": "221", "upper_bound": "237"}, "Division III": {"lower_bound": "240", "upper_bound": "255"}, "Division IV": {"lower_bound": "263", "upper_bound": "274"}}}, {"Rank": "Bronze II", "Players": "1_065", "Player_Percentage": "0.09", "Divisions": {"Division I": {"lower_bound": "155", "upper_bound": "158"}, "Division II": {"lower_bound": "164", "upper_bound": "177"}, "Division III": {"lower_bound": "183", "upper_bound": "195"}, "Division IV": {"lower_bound": "199", "upper_bound": "213"}}}, {"Rank": "Bronze I", "Players": "407", "Player_Percentage": "0.03", "Divisions": {"Division II": {"lower_bound": "126", "upper_bound": "126"}, "Division III": {"lower_bound": "129", "upper_bound": "134"}, "Division IV": {"lower_bound": "144", "upper_bound": "152"}}}, {"Rank": "Unranked", "Players": "120_375", "Player_Percentage": "10.31", "Divisions": {"Division I": {"lower_bound": "504", "upper_bound": "774"}}}]}, "Ranked Standard 3v3": {"Ranks": [{"Rank": "Supersonic Legend", "Players": "1_062", "Player_Percentage": "0.09", "Divisions": {"Division I": {"lower_bound": "1_356", "upper_bound": "1_528"}}}, {"Rank": "Grand Champion III", "Players": "1_365", "Player_Percentage": "0.12", "Divisions": {"Division I": {"lower_bound": "1_290", "upper_bound": "1_298"}, "Division II": {"lower_bound": "1_299", "upper_bound": "1_315"}, "Division III": {"lower_bound": "1_318", "upper_bound": "1_333"}, "Division IV": {"lower_bound": "1_338", "upper_bound": "1_353"}}}, {"Rank": "Grand Champion II", "Players": "1_724", "Player_Percentage": "0.15", "Divisions": {"Division I": {"lower_bound": "1_235", "upper_bound": "1_238"}, "Division II": {"lower_bound": "1_241", "upper_bound": "1_256"}, "Division III": {"lower_bound": "1_258", "upper_bound": "1_275"}, "Division IV": {"lower_bound": "1_277", "upper_bound": "1_294"}}}, {"Rank": "Grand Champion I", "Players": "3_128", "Player_Percentage": "0.27", "Divisions": {"Division I": {"lower_bound": "1_175", "upper_bound": "1_178"}, "Division II": {"lower_bound": "1_180", "upper_bound": "1_196"}, "Division III": {"lower_bound": "1_198", "upper_bound": "1_215"}, "Division IV": {"lower_bound": "1_217", "upper_bound": "1_234"}}}, {"Rank": "Champion III", "Players": "6_035", "Player_Percentage": "0.52", "Divisions": {"Division I": {"lower_bound": "1_115", "upper_bound": "1_118"}, "Division II": {"lower_bound": "1_121", "upper_bound": "1_136"}, "Division III": {"lower_bound": "1_138", "upper_bound": "1_147"}, "Division IV": {"lower_bound": "1_157", "upper_bound": "1_172"}}}, {"Rank": "Champion II", "Players": "11_200", "Player_Percentage": "0.96", "Divisions": {"Division I": {"lower_bound": "1_055", "upper_bound": "1_058"}, "Division II": {"lower_bound": "1_060", "upper_bound": "1_077"}, "Division III": {"lower_bound": "1_078", "upper_bound": "1_094"}, "Division IV": {"lower_bound": "1_097", "upper_bound": "1_112"}}}, {"Rank": "Champion I", "Players": "20_852", "Player_Percentage": "1.79", "Divisions": {"Division I": {"lower_bound": "995", "upper_bound": "998"}, "Division II": {"lower_bound": "1_000", "upper_bound": "1_007"}, "Division III": {"lower_bound": "1_018", "upper_bound": "1_028"}, "Division IV": {"lower_bound": "1_037", "upper_bound": "1_050"}}}, {"Rank": "Diamond III", "Players": "39_219", "Player_Percentage": "3.36", "Divisions": {"Division I": {"lower_bound": "935", "upper_bound": "938"}, "Division II": {"lower_bound": "940", "upper_bound": "957"}, "Division III": {"lower_bound": "958", "upper_bound": "973"}, "Division IV": {"lower_bound": "977", "upper_bound": "993"}}}, {"Rank": "Diamond II", "Players": "63_298", "Player_Percentage": "5.42", "Divisions": {"Division I": {"lower_bound": "875", "upper_bound": "878"}, "Division II": {"lower_bound": "880", "upper_bound": "893"}, "Division III": {"lower_bound": "898", "upper_bound": "909"}, "Division IV": {"lower_bound": "917", "upper_bound": "931"}}}, {"Rank": "Diamond I", "Players": "98_616", "Player_Percentage": "8.45", "Divisions": {"Division I": {"lower_bound": "815", "upper_bound": "818"}, "Division II": {"lower_bound": "820", "upper_bound": "837"}, "Division III": {"lower_bound": "838", "upper_bound": "855"}, "Division IV": {"lower_bound": "857", "upper_bound": "874"}}}, {"Rank": "Platinum III", "Players": "136_851", "Player_Percentage": "11.73", "Divisions": {"Division I": {"lower_bound": "755", "upper_bound": "758"}, "Division II": {"lower_bound": "759", "upper_bound": "777"}, "Division III": {"lower_bound": "778", "upper_bound": "793"}, "Division IV": {"lower_bound": "797", "upper_bound": "810"}}}, {"Rank": "Platinum II", "Players": "162_222", "Player_Percentage": "13.90", "Divisions": {"Division I": {"lower_bound": "695", "upper_bound": "698"}, "Division II": {"lower_bound": "699", "upper_bound": "717"}, "Division III": {"lower_bound": "718", "upper_bound": "735"}, "Division IV": {"lower_bound": "737", "upper_bound": "754"}}}, {"Rank": "Platinum I", "Players": "166_646", "Player_Percentage": "14.28", "Divisions": {"Division I": {"lower_bound": "635", "upper_bound": "638"}, "Division II": {"lower_bound": "639", "upper_bound": "657"}, "Division III": {"lower_bound": "658", "upper_bound": "676"}, "Division IV": {"lower_bound": "677", "upper_bound": "694"}}}, {"Rank": "Gold III", "Players": "131_022", "Player_Percentage": "11.23", "Divisions": {"Division I": {"lower_bound": "575", "upper_bound": "578"}, "Division II": {"lower_bound": "580", "upper_bound": "597"}, "Division III": {"lower_bound": "598", "upper_bound": "615"}, "Division IV": {"lower_bound": "617", "upper_bound": "634"}}}, {"Rank": "Gold II", "Players": "92_427", "Player_Percentage": "7.92", "Divisions": {"Division I": {"lower_bound": "515", "upper_bound": "518"}, "Division II": {"lower_bound": "520", "upper_bound": "537"}, "Division III": {"lower_bound": "538", "upper_bound": "556"}, "Division IV": {"lower_bound": "557", "upper_bound": "574"}}}, {"Rank": "Gold I", "Players": "56_654", "Player_Percentage": "4.85", "Divisions": {"Division I": {"lower_bound": "455", "upper_bound": "458"}, "Division II": {"lower_bound": "460", "upper_bound": "477"}, "Division III": {"lower_bound": "478", "upper_bound": "495"}, "Division IV": {"lower_bound": "497", "upper_bound": "514"}}}, {"Rank": "Silver III", "Players": "29_468", "Player_Percentage": "2.52", "Divisions": {"Division I": {"lower_bound": "395", "upper_bound": "398"}, "Division II": {"lower_bound": "400", "upper_bound": "417"}, "Division III": {"lower_bound": "423", "upper_bound": "435"}, "Division IV": {"lower_bound": "437", "upper_bound": "454"}}}, {"Rank": "Silver II", "Players": "14_517", "Player_Percentage": "1.24", "Divisions": {"Division I": {"lower_bound": "335", "upper_bound": "338"}, "Division II": {"lower_bound": "344", "upper_bound": "357"}, "Division III": {"lower_bound": "364", "upper_bound": "375"}, "Division IV": {"lower_bound": "377", "upper_bound": "394"}}}, {"Rank": "Silver I", "Players": "6_357", "Player_Percentage": "0.54", "Divisions": {"Division I": {"lower_bound": "275", "upper_bound": "278"}, "Division II": {"lower_bound": "280", "upper_bound": "297"}, "Division III": {"lower_bound": "301", "upper_bound": "315"}, "Division IV": {"lower_bound": "317", "upper_bound": "334"}}}, {"Rank": "Bronze III", "Players": "2_617", "Player_Percentage": "0.22", "Divisions": {"Division I": {"lower_bound": "215", "upper_bound": "218"}, "Division II": {"lower_bound": "221", "upper_bound": "237"}, "Division III": {"lower_bound": "240", "upper_bound": "255"}, "Division IV": {"lower_bound": "263", "upper_bound": "274"}}}, {"Rank": "Bronze II", "Players": "1_065", "Player_Percentage": "0.09", "Divisions": {"Division I": {"lower_bound": "155", "upper_bound": "158"}, "Division II": {"lower_bound": "164", "upper_bound": "177"}, "Division III": {"lower_bound": "183", "upper_bound": "195"}, "Division IV": {"lower_bound": "199", "upper_bound": "213"}}}, {"Rank": "Bronze I", "Players": "407", "Player_Percentage": "0.03", "Divisions": {"Division II": {"lower_bound": "126", "upper_bound": "126"}, "Division III": {"lower_bound": "129", "upper_bound": "134"}, "Division IV": {"lower_bound": "144", "upper_bound": "152"}}}, {"Rank": "Unranked", "Players": "120_375", "Player_Percentage": "10.31", "Divisions": {"Division I": {"lower_bound": "504", "upper_bound": "774"}}}]}, "Hoops": {"Ranks": [{"Rank": "Supersonic Legend", "Players": "1_062", "Player_Percentage": "0.09", "Divisions": {"Division I": {"lower_bound": "1_356", "upper_bound": "1_528"}}}, {"Rank": "Grand Champion III", "Players": "1_365", "Player_Percentage": "0.12", "Divisions": {"Division I": {"lower_bound": "1_290", "upper_bound": "1_298"}, "Division II": {"lower_bound": "1_299", "upper_bound": "1_315"}, "Division III": {"lower_bound": "1_318", "upper_bound": "1_333"}, "Division IV": {"lower_bound": "1_338", "upper_bound": "1_353"}}}, {"Rank": "Grand Champion II", "Players": "1_724", "Player_Percentage": "0.15", "Divisions": {"Division I": {"lower_bound": "1_235", "upper_bound": "1_238"}, "Division II": {"lower_bound": "1_241", "upper_bound": "1_256"}, "Division III": {"lower_bound": "1_258", "upper_bound": "1_275"}, "Division IV": {"lower_bound": "1_277", "upper_bound": "1_294"}}}, {"Rank": "Grand Champion I", "Players": "3_128", "Player_Percentage": "0.27", "Divisions": {"Division I": {"lower_bound": "1_175", "upper_bound": "1_178"}, "Division II": {"lower_bound": "1_180", "upper_bound": "1_196"}, "Division III": {"lower_bound": "1_198", "upper_bound": "1_215"}, "Division IV": {"lower_bound": "1_217", "upper_bound": "1_234"}}}, {"Rank": "Champion III", "Players": "6_035", "Player_Percentage": "0.52", "Divisions": {"Division I": {"lower_bound": "1_115", "upper_bound": "1_118"}, "Division II": {"lower_bound": "1_121", "upper_bound": "1_136"}, "Division III": {"lower_bound": "1_138", "upper_bound": "1_147"}, "Division IV": {"lower_bound": "1_157", "upper_bound": "1_172"}}}, {"Rank": "Champion II", "Players": "11_200", "Player_Percentage": "0.96", "Divisions": {"Division I": {"lower_bound": "1_055", "upper_bound": "1_058"}, "Division II": {"lower_bound": "1_060", "upper_bound": "1_077"}, "Division III": {"lower_bound": "1_078", "upper_bound": "1_094"}, "Division IV": {"lower_bound": "1_097", "upper_bound": "1_112"}}}, {"Rank": "Champion I", "Players": "20_852", "Player_Percentage": "1.79", "Divisions": {"Division I": {"lower_bound": "995", "upper_bound": "998"}, "Division II": {"lower_bound": "1_000", "upper_bound": "1_007"}, "Division III": {"lower_bound": "1_018", "upper_bound": "1_028"}, "Division IV": {"lower_bound": "1_037", "upper_bound": "1_050"}}}, {"Rank": "Diamond III", "Players": "39_219", "Player_Percentage": "3.36", "Divisions": {"Division I": {"lower_bound": "935", "upper_bound": "938"}, "Division II": {"lower_bound": "940", "upper_bound": "957"}, "Division III": {"lower_bound": "958", "upper_bound": "973"}, "Division IV": {"lower_bound": "977", "upper_bound": "993"}}}, {"Rank": "Diamond II", "Players": "63_298", "Player_Percentage": "5.42", "Divisions": {"Division I": {"lower_bound": "875", "upper_bound": "878"}, "Division II": {"lower_bound": "880", "upper_bound": "893"}, "Division III": {"lower_bound": "898", "upper_bound": "909"}, "Division IV": {"lower_bound": "917", "upper_bound": "931"}}}, {"Rank": "Diamond I", "Players": "98_616", "Player_Percentage": "8.45", "Divisions": {"Division I": {"lower_bound": "815", "upper_bound": "818"}, "Division II": {"lower_bound": "820", "upper_bound": "837"}, "Division III": {"lower_bound": "838", "upper_bound": "855"}, "Division IV": {"lower_bound": "857", "upper_bound": "874"}}}, {"Rank": "Platinum III", "Players": "136_851", "Player_Percentage": "11.73", "Divisions": {"Division I": {"lower_bound": "755", "upper_bound": "758"}, "Division II": {"lower_bound": "759", "upper_bound": "777"}, "Division III": {"lower_bound": "778", "upper_bound": "793"}, "Division IV": {"lower_bound": "797", "upper_bound": "810"}}}, {"Rank": "Platinum II", "Players": "162_222", "Player_Percentage": "13.90", "Divisions": {"Division I": {"lower_bound": "695", "upper_bound": "698"}, "Division II": {"lower_bound": "699", "upper_bound": "717"}, "Division III": {"lower_bound": "718", "upper_bound": "735"}, "Division IV": {"lower_bound": "737", "upper_bound": "754"}}}, {"Rank": "Platinum I", "Players": "166_646", "Player_Percentage": "14.28", "Divisions": {"Division I": {"lower_bound": "635", "upper_bound": "638"}, "Division II": {"lower_bound": "639", "upper_bound": "657"}, "Division III": {"lower_bound": "658", "upper_bound": "676"}, "Division IV": {"lower_bound": "677", "upper_bound": "694"}}}, {"Rank": "Gold III", "Players": "131_022", "Player_Percentage": "11.23", "Divisions": {"Division I": {"lower_bound": "575", "upper_bound": "578"}, "Division II": {"lower_bound": "580", "upper_bound": "597"}, "Division III": {"lower_bound": "598", "upper_bound": "615"}, "Division IV": {"lower_bound": "617", "upper_bound": "634"}}}, {"Rank": "Gold II", "Players": "92_427", "Player_Percentage": "7.92", "Divisions": {"Division I": {"lower_bound": "515", "upper_bound": "518"}, "Division II": {"lower_bound": "520", "upper_bound": "537"}, "Division III": {"lower_bound": "538", "upper_bound": "556"}, "Division IV": {"lower_bound": "557", "upper_bound": "574"}}}, {"Rank": "Gold I", "Players": "56_654", "Player_Percentage": "4.85", "Divisions": {"Division I": {"lower_bound": "455", "upper_bound": "458"}, "Division II": {"lower_bound": "460", "upper_bound": "477"}, "Division III": {"lower_bound": "478", "upper_bound": "495"}, "Division IV": {"lower_bound": "497", "upper_bound": "514"}}}, {"Rank": "Silver III", "Players": "29_468", "Player_Percentage": "2.52", "Divisions": {"Division I": {"lower_bound": "395", "upper_bound": "398"}, "Division II": {"lower_bound": "400", "upper_bound": "417"}, "Division III": {"lower_bound": "423", "upper_bound": "435"}, "Division IV": {"lower_bound": "437", "upper_bound": "454"}}}, {"Rank": "Silver II", "Players": "14_517", "Player_Percentage": "1.24", "Divisions": {"Division I": {"lower_bound": "335", "upper_bound": "338"}, "Division II": {"lower_bound": "344", "upper_bound": "357"}, "Division III": {"lower_bound": "364", "upper_bound": "375"}, "Division IV": {"lower_bound": "377", "upper_bound": "394"}}}, {"Rank": "Silver I", "Players": "6_357", "Player_Percentage": "0.54", "Divisions": {"Division I": {"lower_bound": "275", "upper_bound": "278"}, "Division II": {"lower_bound": "280", "upper_bound": "297"}, "Division III": {"lower_bound": "301", "upper_bound": "315"}, "Division IV": {"lower_bound": "317", "upper_bound": "334"}}}, {"Rank": "Bronze III", "Players": "2_617", "Player_Percentage": "0.22", "Divisions": {"Division I": {"lower_bound": "215", "upper_bound": "218"}, "Division II": {"lower_bound": "221", "upper_bound": "237"}, "Division III": {"lower_bound": "240", "upper_bound": "255"}, "Division IV": {"lower_bound": "263", "upper_bound": "274"}}}, {"Rank": "Bronze II", "Players": "1_065", "Player_Percentage": "0.09", "Divisions": {"Division I": {"lower_bound": "155", "upper_bound": "158"}, "Division II": {"lower_bound": "164", "upper_bound": "177"}, "Division III": {"lower_bound": "183", "upper_bound": "195"}, "Division IV": {"lower_bound": "199", "upper_bound": "213"}}}, {"Rank": "Bronze I", "Players": "407", "Player_Percentage": "0.03", "Divisions": {"Division II": {"lower_bound": "126", "upper_bound": "126"}, "Division III": {"lower_bound": "129", "upper_bound": "134"}, "Division IV": {"lower_bound": "144", "upper_bound": "152"}}}, {"Rank": "Unranked", "Players": "120_375", "Player_Percentage": "10.31", "Divisions": {"Division I": {"lower_bound": "504", "upper_bound": "774"}}}]}, "Rumble": {"Ranks": [{"Rank": "Supersonic Legend", "Players": "1_062", "Player_Percentage": "0.09", "Divisions": {"Division I": {"lower_bound": "1_356", "upper_bound": "1_528"}}}, {"Rank": "Grand Champion III", "Players": "1_365", "Player_Percentage": "0.12", "Divisions": {"Division I": {"lower_bound": "1_290", "upper_bound": "1_298"}, "Division II": {"lower_bound": "1_299", "upper_bound": "1_315"}, "Division III": {"lower_bound": "1_318", "upper_bound": "1_333"}, "Division IV": {"lower_bound": "1_338", "upper_bound": "1_353"}}}, {"Rank": "Grand Champion II", "Players": "1_724", "Player_Percentage": "0.15", "Divisions": {"Division I": {"lower_bound": "1_235", "upper_bound": "1_238"}, "Division II": {"lower_bound": "1_241", "upper_bound": "1_256"}, "Division III": {"lower_bound": "1_258", "upper_bound": "1_275"}, "Division IV": {"lower_bound": "1_277", "upper_bound": "1_294"}}}, {"Rank": "Grand Champion I", "Players": "3_128", "Player_Percentage": "0.27", "Divisions": {"Division I": {"lower_bound": "1_175", "upper_bound": "1_178"}, "Division II": {"lower_bound": "1_180", "upper_bound": "1_196"}, "Division III": {"lower_bound": "1_198", "upper_bound": "1_215"}, "Division IV": {"lower_bound": "1_217", "upper_bound": "1_234"}}}, {"Rank": "Champion III", "Players": "6_035", "Player_Percentage": "0.52", "Divisions": {"Division I": {"lower_bound": "1_115", "upper_bound": "1_118"}, "Division II": {"lower_bound": "1_121", "upper_bound": "1_136"}, "Division III": {"lower_bound": "1_138", "upper_bound": "1_147"}, "Division IV": {"lower_bound": "1_157", "upper_bound": "1_172"}}}, {"Rank": "Champion II", "Players": "11_200", "Player_Percentage": "0.96", "Divisions": {"Division I": {"lower_bound": "1_055", "upper_bound": "1_058"}, "Division II": {"lower_bound": "1_060", "upper_bound": "1_077"}, "Division III": {"lower_bound": "1_078", "upper_bound": "1_094"}, "Division IV": {"lower_bound": "1_097", "upper_bound": "1_112"}}}, {"Rank": "Champion I", "Players": "20_852", "Player_Percentage": "1.79", "Divisions": {"Division I": {"lower_bound": "995", "upper_bound": "998"}, "Division II": {"lower_bound": "1_000", "upper_bound": "1_007"}, "Division III": {"lower_bound": "1_018", "upper_bound": "1_028"}, "Division IV": {"lower_bound": "1_037", "upper_bound": "1_050"}}}, {"Rank": "Diamond III", "Players": "39_219", "Player_Percentage": "3.36", "Divisions": {"Division I": {"lower_bound": "935", "upper_bound": "938"}, "Division II": {"lower_bound": "940", "upper_bound": "957"}, "Division III": {"lower_bound": "958", "upper_bound": "973"}, "Division IV": {"lower_bound": "977", "upper_bound": "993"}}}, {"Rank": "Diamond II", "Players": "63_298", "Player_Percentage": "5.42", "Divisions": {"Division I": {"lower_bound": "875", "upper_bound": "878"}, "Division II": {"lower_bound": "880", "upper_bound": "893"}, "Division III": {"lower_bound": "898", "upper_bound": "909"}, "Division IV": {"lower_bound": "917", "upper_bound": "931"}}}, {"Rank": "Diamond I", "Players": "98_616", "Player_Percentage": "8.45", "Divisions": {"Division I": {"lower_bound": "815", "upper_bound": "818"}, "Division II": {"lower_bound": "820", "upper_bound": "837"}, "Division III": {"lower_bound": "838", "upper_bound": "855"}, "Division IV": {"lower_bound": "857", "upper_bound": "874"}}}, {"Rank": "Platinum III", "Players": "136_851", "Player_Percentage": "11.73", "Divisions": {"Division I": {"lower_bound": "755", "upper_bound": "758"}, "Division II": {"lower_bound": "759", "upper_bound": "777"}, "Division III": {"lower_bound": "778", "upper_bound": "793"}, "Division IV": {"lower_bound": "797", "upper_bound": "810"}}}, {"Rank": "Platinum II", "Players": "162_222", "Player_Percentage": "13.90", "Divisions": {"Division I": {"lower_bound": "695", "upper_bound": "698"}, "Division II": {"lower_bound": "699", "upper_bound": "717"}, "Division III": {"lower_bound": "718", "upper_bound": "735"}, "Division IV": {"lower_bound": "737", "upper_bound": "754"}}}, {"Rank": "Platinum I", "Players": "166_646", "Player_Percentage": "14.28", "Divisions": {"Division I": {"lower_bound": "635", "upper_bound": "638"}, "Division II": {"lower_bound": "639", "upper_bound": "657"}, "Division III": {"lower_bound": "658", "upper_bound": "676"}, "Division IV": {"lower_bound": "677", "upper_bound": "694"}}}, {"Rank": "Gold III", "Players": "131_022", "Player_Percentage": "11.23", "Divisions": {"Division I": {"lower_bound": "575", "upper_bound": "578"}, "Division II": {"lower_bound": "580", "upper_bound": "597"}, "Division III": {"lower_bound": "598", "upper_bound": "615"}, "Division IV": {"lower_bound": "617", "upper_bound": "634"}}}, {"Rank": "Gold II", "Players": "92_427", "Player_Percentage": "7.92", "Divisions": {"Division I": {"lower_bound": "515", "upper_bound": "518"}, "Division II": {"lower_bound": "520", "upper_bound": "537"}, "Division III": {"lower_bound": "538", "upper_bound": "556"}, "Division IV": {"lower_bound": "557", "upper_bound": "574"}}}, {"Rank": "Gold I", "Players": "56_654", "Player_Percentage": "4.85", "Divisions": {"Division I": {"lower_bound": "455", "upper_bound": "458"}, "Division II": {"lower_bound": "460", "upper_bound": "477"}, "Division III": {"lower_bound": "478", "upper_bound": "495"}, "Division IV": {"lower_bound": "497", "upper_bound": "514"}}}, {"Rank": "Silver III", "Players": "29_468", "Player_Percentage": "2.52", "Divisions": {"Division I": {"lower_bound": "395", "upper_bound": "398"}, "Division II": {"lower_bound": "400", "upper_bound": "417"}, "Division III": {"lower_bound": "423", "upper_bound": "435"}, "Division IV": {"lower_bound": "437", "upper_bound": "454"}}}, {"Rank": "Silver II", "Players": "14_517", "Player_Percentage": "1.24", "Divisions": {"Division I": {"lower_bound": "335", "upper_bound": "338"}, "Division II": {"lower_bound": "344", "upper_bound": "357"}, "Division III": {"lower_bound": "364", "upper_bound": "375"}, "Division IV": {"lower_bound": "377", "upper_bound": "394"}}}, {"Rank": "Silver I", "Players": "6_357", "Player_Percentage": "0.54", "Divisions": {"Division I": {"lower_bound": "275", "upper_bound": "278"}, "Division II": {"lower_bound": "280", "upper_bound": "297"}, "Division III": {"lower_bound": "301", "upper_bound": "315"}, "Division IV": {"lower_bound": "317", "upper_bound": "334"}}}, {"Rank": "Bronze III", "Players": "2_617", "Player_Percentage": "0.22", "Divisions": {"Division I": {"lower_bound": "215", "upper_bound": "218"}, "Division II": {"lower_bound": "221", "upper_bound": "237"}, "Division III": {"lower_bound": "240", "upper_bound": "255"}, "Division IV": {"lower_bound": "263", "upper_bound": "274"}}}, {"Rank": "Bronze II", "Players": "1_065", "Player_Percentage": "0.09", "Divisions": {"Division I": {"lower_bound": "155", "upper_bound": "158"}, "Division II": {"lower_bound": "164", "upper_bound": "177"}, "Division III": {"lower_bound": "183", "upper_bound": "195"}, "Division IV": {"lower_bound": "199", "upper_bound": "213"}}}, {"Rank": "Bronze I", "Players": "407", "Player_Percentage": "0.03", "Divisions": {"Division II": {"lower_bound": "126", "upper_bound": "126"}, "Division III": {"lower_bound": "129", "upper_bound": "134"}, "Division IV": {"lower_bound": "144", "upper_bound": "152"}}}, {"Rank": "Unranked", "Players": "120_375", "Player_Percentage": "10.31", "Divisions": {"Division I": {"lower_bound": "504", "upper_bound": "774"}}}]}, "Dropshot": {"Ranks": [{"Rank": "Supersonic Legend", "Players": "1_062", "Player_Percentage": "0.09", "Divisions": {"Division I": {"lower_bound": "1_356", "upper_bound": "1_528"}}}, {"Rank": "Grand Champion III", "Players": "1_365", "Player_Percentage": "0.12", "Divisions": {"Division I": {"lower_bound": "1_290", "upper_bound": "1_298"}, "Division II": {"lower_bound": "1_299", "upper_bound": "1_315"}, "Division III": {"lower_bound": "1_318", "upper_bound": "1_333"}, "Division IV": {"lower_bound": "1_338", "upper_bound": "1_353"}}}, {"Rank": "Grand Champion II", "Players": "1_724", "Player_Percentage": "0.15", "Divisions": {"Division I": {"lower_bound": "1_235", "upper_bound": "1_238"}, "Division II": {"lower_bound": "1_241", "upper_bound": "1_256"}, "Division III": {"lower_bound": "1_258", "upper_bound": "1_275"}, "Division IV": {"lower_bound": "1_277", "upper_bound": "1_294"}}}, {"Rank": "Grand Champion I", "Players": "3_128", "Player_Percentage": "0.27", "Divisions": {"Division I": {"lower_bound": "1_175", "upper_bound": "1_178"}, "Division II": {"lower_bound": "1_180", "upper_bound": "1_196"}, "Division III": {"lower_bound": "1_198", "upper_bound": "1_215"}, "Division IV": {"lower_bound": "1_217", "upper_bound": "1_234"}}}, {"Rank": "Champion III", "Players": "6_035", "Player_Percentage": "0.52", "Divisions": {"Division I": {"lower_bound": "1_115", "upper_bound": "1_118"}, "Division II": {"lower_bound": "1_121", "upper_bound": "1_136"}, "Division III": {"lower_bound": "1_138", "upper_bound": "1_147"}, "Division IV": {"lower_bound": "1_157", "upper_bound": "1_172"}}}, {"Rank": "Champion II", "Players": "11_200", "Player_Percentage": "0.96", "Divisions": {"Division I": {"lower_bound": "1_055", "upper_bound": "1_058"}, "Division II": {"lower_bound": "1_060", "upper_bound": "1_077"}, "Division III": {"lower_bound": "1_078", "upper_bound": "1_094"}, "Division IV": {"lower_bound": "1_097", "upper_bound": "1_112"}}}, {"Rank": "Champion I", "Players": "20_852", "Player_Percentage": "1.79", "Divisions": {"Division I": {"lower_bound": "995", "upper_bound": "998"}, "Division II": {"lower_bound": "1_000", "upper_bound": "1_007"}, "Division III": {"lower_bound": "1_018", "upper_bound": "1_028"}, "Division IV": {"lower_bound": "1_037", "upper_bound": "1_050"}}}, {"Rank": "Diamond III", "Players": "39_219", "Player_Percentage": "3.36", "Divisions": {"Division I": {"lower_bound": "935", "upper_bound": "938"}, "Division II": {"lower_bound": "940", "upper_bound": "957"}, "Division III": {"lower_bound": "958", "upper_bound": "973"}, "Division IV": {"lower_bound": "977", "upper_bound": "993"}}}, {"Rank": "Diamond II", "Players": "63_298", "Player_Percentage": "5.42", "Divisions": {"Division I": {"lower_bound": "875", "upper_bound": "878"}, "Division II": {"lower_bound": "880", "upper_bound": "893"}, "Division III": {"lower_bound": "898", "upper_bound": "909"}, "Division IV": {"lower_bound": "917", "upper_bound": "931"}}}, {"Rank": "Diamond I", "Players": "98_616", "Player_Percentage": "8.45", "Divisions": {"Division I": {"lower_bound": "815", "upper_bound": "818"}, "Division II": {"lower_bound": "820", "upper_bound": "837"}, "Division III": {"lower_bound": "838", "upper_bound": "855"}, "Division IV": {"lower_bound": "857", "upper_bound": "874"}}}, {"Rank": "Platinum III", "Players": "136_851", "Player_Percentage": "11.73", "Divisions": {"Division I": {"lower_bound": "755", "upper_bound": "758"}, "Division II": {"lower_bound": "759", "upper_bound": "777"}, "Division III": {"lower_bound": "778", "upper_bound": "793"}, "Division IV": {"lower_bound": "797", "upper_bound": "810"}}}, {"Rank": "Platinum II", "Players": "162_222", "Player_Percentage": "13.90", "Divisions": {"Division I": {"lower_bound": "695", "upper_bound": "698"}, "Division II": {"lower_bound": "699", "upper_bound": "717"}, "Division III": {"lower_bound": "718", "upper_bound": "735"}, "Division IV": {"lower_bound": "737", "upper_bound": "754"}}}, {"Rank": "Platinum I", "Players": "166_646", "Player_Percentage": "14.28", "Divisions": {"Division I": {"lower_bound": "635", "upper_bound": "638"}, "Division II": {"lower_bound": "639", "upper_bound": "657"}, "Division III": {"lower_bound": "658", "upper_bound": "676"}, "Division IV": {"lower_bound": "677", "upper_bound": "694"}}}, {"Rank": "Gold III", "Players": "131_022", "Player_Percentage": "11.23", "Divisions": {"Division I": {"lower_bound": "575", "upper_bound": "578"}, "Division II": {"lower_bound": "580", "upper_bound": "597"}, "Division III": {"lower_bound": "598", "upper_bound": "615"}, "Division IV": {"lower_bound": "617", "upper_bound": "634"}}}, {"Rank": "Gold II", "Players": "92_427", "Player_Percentage": "7.92", "Divisions": {"Division I": {"lower_bound": "515", "upper_bound": "518"}, "Division II": {"lower_bound": "520", "upper_bound": "537"}, "Division III": {"lower_bound": "538", "upper_bound": "556"}, "Division IV": {"lower_bound": "557", "upper_bound": "574"}}}, {"Rank": "Gold I", "Players": "56_654", "Player_Percentage": "4.85", "Divisions": {"Division I": {"lower_bound": "455", "upper_bound": "458"}, "Division II": {"lower_bound": "460", "upper_bound": "477"}, "Division III": {"lower_bound": "478", "upper_bound": "495"}, "Division IV": {"lower_bound": "497", "upper_bound": "514"}}}, {"Rank": "Silver III", "Players": "29_468", "Player_Percentage": "2.52", "Divisions": {"Division I": {"lower_bound": "395", "upper_bound": "398"}, "Division II": {"lower_bound": "400", "upper_bound": "417"}, "Division III": {"lower_bound": "423", "upper_bound": "435"}, "Division IV": {"lower_bound": "437", "upper_bound": "454"}}}, {"Rank": "Silver II", "Players": "14_517", "Player_Percentage": "1.24", "Divisions": {"Division I": {"lower_bound": "335", "upper_bound": "338"}, "Division II": {"lower_bound": "344", "upper_bound": "357"}, "Division III": {"lower_bound": "364", "upper_bound": "375"}, "Division IV": {"lower_bound": "377", "upper_bound": "394"}}}, {"Rank": "Silver I", "Players": "6_357", "Player_Percentage": "0.54", "Divisions": {"Division I": {"lower_bound": "275", "upper_bound": "278"}, "Division II": {"lower_bound": "280", "upper_bound": "297"}, "Division III": {"lower_bound": "301", "upper_bound": "315"}, "Division IV": {"lower_bound": "317", "upper_bound": "334"}}}, {"Rank": "Bronze III", "Players": "2_617", "Player_Percentage": "0.22", "Divisions": {"Division I": {"lower_bound": "215", "upper_bound": "218"}, "Division II": {"lower_bound": "221", "upper_bound": "237"}, "Division III": {"lower_bound": "240", "upper_bound": "255"}, "Division IV": {"lower_bound": "263", "upper_bound": "274"}}}, {"Rank": "Bronze II", "Players": "1_065", "Player_Percentage": "0.09", "Divisions": {"Division I": {"lower_bound": "155", "upper_bound": "158"}, "Division II": {"lower_bound": "164", "upper_bound": "177"}, "Division III": {"lower_bound": "183", "upper_bound": "195"}, "Division IV": {"lower_bound": "199", "upper_bound": "213"}}}, {"Rank": "Bronze I", "Players": "407", "Player_Percentage": "0.03", "Divisions": {"Division II": {"lower_bound": "126", "upper_bound": "126"}, "Division III": {"lower_bound": "129", "upper_bound": "134"}, "Division IV": {"lower_bound": "144", "upper_bound": "152"}}}, {"Rank": "Unranked", "Players": "120_375", "Player_Percentage": "10.31", "Divisions": {"Division I": {"lower_bound": "504", "upper_bound": "774"}}}]}, "Snowday": {"Ranks": [{"Rank": "Supersonic Legend", "Players": "1_062", "Player_Percentage": "0.09", "Divisions": {"Division I": {"lower_bound": "1_356", "upper_bound": "1_528"}}}, {"Rank": "Grand Champion III", "Players": "1_365", "Player_Percentage": "0.12", "Divisions": {"Division I": {"lower_bound": "1_290", "upper_bound": "1_298"}, "Division II": {"lower_bound": "1_299", "upper_bound": "1_315"}, "Division III": {"lower_bound": "1_318", "upper_bound": "1_333"}, "Division IV": {"lower_bound": "1_338", "upper_bound": "1_353"}}}, {"Rank": "Grand Champion II", "Players": "1_724", "Player_Percentage": "0.15", "Divisions": {"Division I": {"lower_bound": "1_235", "upper_bound": "1_238"}, "Division II": {"lower_bound": "1_241", "upper_bound": "1_256"}, "Division III": {"lower_bound": "1_258", "upper_bound": "1_275"}, "Division IV": {"lower_bound": "1_277", "upper_bound": "1_294"}}}, {"Rank": "Grand Champion I", "Players": "3_128", "Player_Percentage": "0.27", "Divisions": {"Division I": {"lower_bound": "1_175", "upper_bound": "1_178"}, "Division II": {"lower_bound": "1_180", "upper_bound": "1_196"}, "Division III": {"lower_bound": "1_198", "upper_bound": "1_215"}, "Division IV": {"lower_bound": "1_217", "upper_bound": "1_234"}}}, {"Rank": "Champion III", "Players": "6_035", "Player_Percentage": "0.52", "Divisions": {"Division I": {"lower_bound": "1_115", "upper_bound": "1_118"}, "Division II": {"lower_bound": "1_121", "upper_bound": "1_136"}, "Division III": {"lower_bound": "1_138", "upper_bound": "1_147"}, "Division IV": {"lower_bound": "1_157", "upper_bound": "1_172"}}}, {"Rank": "Champion II", "Players": "11_200", "Player_Percentage": "0.96", "Divisions": {"Division I": {"lower_bound": "1_055", "upper_bound": "1_058"}, "Division II": {"lower_bound": "1_060", "upper_bound": "1_077"}, "Division III": {"lower_bound": "1_078", "upper_bound": "1_094"}, "Division IV": {"lower_bound": "1_097", "upper_bound": "1_112"}}}, {"Rank": "Champion I", "Players": "20_852", "Player_Percentage": "1.79", "Divisions": {"Division I": {"lower_bound": "995", "upper_bound": "998"}, "Division II": {"lower_bound": "1_000", "upper_bound": "1_007"}, "Division III": {"lower_bound": "1_018", "upper_bound": "1_028"}, "Division IV": {"lower_bound": "1_037", "upper_bound": "1_050"}}}, {"Rank": "Diamond III", "Players": "39_219", "Player_Percentage": "3.36", "Divisions": {"Division I": {"lower_bound": "935", "upper_bound": "938"}, "Division II": {"lower_bound": "940", "upper_bound": "957"}, "Division III": {"lower_bound": "958", "upper_bound": "973"}, "Division IV": {"lower_bound": "977", "upper_bound": "993"}}}, {"Rank": "Diamond II", "Players": "63_298", "Player_Percentage": "5.42", "Divisions": {"Division I": {"lower_bound": "875", "upper_bound": "878"}, "Division II": {"lower_bound": "880", "upper_bound": "893"}, "Division III": {"lower_bound": "898", "upper_bound": "909"}, "Division IV": {"lower_bound": "917", "upper_bound": "931"}}}, {"Rank": "Diamond I", "Players": "98_616", "Player_Percentage": "8.45", "Divisions": {"Division I": {"lower_bound": "815", "upper_bound": "818"}, "Division II": {"lower_bound": "820", "upper_bound": "837"}, "Division III": {"lower_bound": "838", "upper_bound": "855"}, "Division IV": {"lower_bound": "857", "upper_bound": "874"}}}, {"Rank": "Platinum III", "Players": "136_851", "Player_Percentage": "11.73", "Divisions": {"Division I": {"lower_bound": "755", "upper_bound": "758"}, "Division II": {"lower_bound": "759", "upper_bound": "777"}, "Division III": {"lower_bound": "778", "upper_bound": "793"}, "Division IV": {"lower_bound": "797", "upper_bound": "810"}}}, {"Rank": "Platinum II", "Players": "162_222", "Player_Percentage": "13.90", "Divisions": {"Division I": {"lower_bound": "695", "upper_bound": "698"}, "Division II": {"lower_bound": "699", "upper_bound": "717"}, "Division III": {"lower_bound": "718", "upper_bound": "735"}, "Division IV": {"lower_bound": "737", "upper_bound": "754"}}}, {"Rank": "Platinum I", "Players": "166_646", "Player_Percentage": "14.28", "Divisions": {"Division I": {"lower_bound": "635", "upper_bound": "638"}, "Division II": {"lower_bound": "639", "upper_bound": "657"}, "Division III": {"lower_bound": "658", "upper_bound": "676"}, "Division IV": {"lower_bound": "677", "upper_bound": "694"}}}, {"Rank": "Gold III", "Players": "131_022", "Player_Percentage": "11.23", "Divisions": {"Division I": {"lower_bound": "575", "upper_bound": "578"}, "Division II": {"lower_bound": "580", "upper_bound": "597"}, "Division III": {"lower_bound": "598", "upper_bound": "615"}, "Division IV": {"lower_bound": "617", "upper_bound": "634"}}}, {"Rank": "Gold II", "Players": "92_427", "Player_Percentage": "7.92", "Divisions": {"Division I": {"lower_bound": "515", "upper_bound": "518"}, "Division II": {"lower_bound": "520", "upper_bound": "537"}, "Division III": {"lower_bound": "538", "upper_bound": "556"}, "Division IV": {"lower_bound": "557", "upper_bound": "574"}}}, {"Rank": "Gold I", "Players": "56_654", "Player_Percentage": "4.85", "Divisions": {"Division I": {"lower_bound": "455", "upper_bound": "458"}, "Division II": {"lower_bound": "460", "upper_bound": "477"}, "Division III": {"lower_bound": "478", "upper_bound": "495"}, "Division IV": {"lower_bound": "497", "upper_bound": "514"}}}, {"Rank": "Silver III", "Players": "29_468", "Player_Percentage": "2.52", "Divisions": {"Division I": {"lower_bound": "395", "upper_bound": "398"}, "Division II": {"lower_bound": "400", "upper_bound": "417"}, "Division III": {"lower_bound": "423", "upper_bound": "435"}, "Division IV": {"lower_bound": "437", "upper_bound": "454"}}}, {"Rank": "Silver II", "Players": "14_517", "Player_Percentage": "1.24", "Divisions": {"Division I": {"lower_bound": "335", "upper_bound": "338"}, "Division II": {"lower_bound": "344", "upper_bound": "357"}, "Division III": {"lower_bound": "364", "upper_bound": "375"}, "Division IV": {"lower_bound": "377", "upper_bound": "394"}}}, {"Rank": "Silver I", "Players": "6_357", "Player_Percentage": "0.54", "Divisions": {"Division I": {"lower_bound": "275", "upper_bound": "278"}, "Division II": {"lower_bound": "280", "upper_bound": "297"}, "Division III": {"lower_bound": "301", "upper_bound": "315"}, "Division IV": {"lower_bound": "317", "upper_bound": "334"}}}, {"Rank": "Bronze III", "Players": "2_617", "Player_Percentage": "0.22", "Divisions": {"Division I": {"lower_bound": "215", "upper_bound": "218"}, "Division II": {"lower_bound": "221", "upper_bound": "237"}, "Division III": {"lower_bound": "240", "upper_bound": "255"}, "Division IV": {"lower_bound": "263", "upper_bound": "274"}}}, {"Rank": "Bronze II", "Players": "1_065", "Player_Percentage": "0.09", "Divisions": {"Division I": {"lower_bound": "155", "upper_bound": "158"}, "Division II": {"lower_bound": "164", "upper_bound": "177"}, "Division III": {"lower_bound": "183", "upper_bound": "195"}, "Division IV": {"lower_bound": "199", "upper_bound": "213"}}}, {"Rank": "Bronze I", "Players": "407", "Player_Percentage": "0.03", "Divisions": {"Division II": {"lower_bound": "126", "upper_bound": "126"}, "Division III": {"lower_bound": "129", "upper_bound": "134"}, "Division IV": {"lower_bound": "144", "upper_bound": "152"}}}, {"Rank": "Unranked", "Players": "120_375", "Player_Percentage": "10.31", "Divisions": {"Division I": {"lower_bound": "504", "upper_bound": "774"}}}]}, "Tournament Matches": {"Ranks": [{"Rank": "Supersonic Legend", "Players": "1_062", "Player_Percentage": "0.09", "Divisions": {"Division I": {"lower_bound": "1_356", "upper_bound": "1_528"}}}, {"Rank": "Grand Champion III", "Players": "1_365", "Player_Percentage": "0.12", "Divisions": {"Division I": {"lower_bound": "1_290", "upper_bound": "1_298"}, "Division II": {"lower_bound": "1_299", "upper_bound": "1_315"}, "Division III": {"lower_bound": "1_318", "upper_bound": "1_333"}, "Division IV": {"lower_bound": "1_338", "upper_bound": "1_353"}}}, {"Rank": "Grand Champion II", "Players": "1_724", "Player_Percentage": "0.15", "Divisions": {"Division I": {"lower_bound": "1_235", "upper_bound": "1_238"}, "Division II": {"lower_bound": "1_241", "upper_bound": "1_256"}, "Division III": {"lower_bound": "1_258", "upper_bound": "1_275"}, "Division IV": {"lower_bound": "1_277", "upper_bound": "1_294"}}}, {"Rank": "Grand Champion I", "Players": "3_128", "Player_Percentage": "0.27", "Divisions": {"Division I": {"lower_bound": "1_175", "upper_bound": "1_178"}, "Division II": {"lower_bound": "1_180", "upper_bound": "1_196"}, "Division III": {"lower_bound": "1_198", "upper_bound": "1_215"}, "Division IV": {"lower_bound": "1_217", "upper_bound": "1_234"}}}, {"Rank": "Champion III", "Players": "6_035", "Player_Percentage": "0.52", "Divisions": {"Division I": {"lower_bound": "1_115", "upper_bound": "1_118"}, "Division II": {"lower_bound": "1_121", "upper_bound": "1_136"}, "Division III": {"lower_bound": "1_138", "upper_bound": "1_147"}, "Division IV": {"lower_bound": "1_157", "upper_bound": "1_172"}}}, {"Rank": "Champion II", "Players": "11_200", "Player_Percentage": "0.96", "Divisions": {"Division I": {"lower_bound": "1_055", "upper_bound": "1_058"}, "Division II": {"lower_bound": "1_060", "upper_bound": "1_077"}, "Division III": {"lower_bound": "1_078", "upper_bound": "1_094"}, "Division IV": {"lower_bound": "1_097", "upper_bound": "1_112"}}}, {"Rank": "Champion I", "Players": "20_852", "Player_Percentage": "1.79", "Divisions": {"Division I": {"lower_bound": "995", "upper_bound": "998"}, "Division II": {"lower_bound": "1_000", "upper_bound": "1_007"}, "Division III": {"lower_bound": "1_018", "upper_bound": "1_028"}, "Division IV": {"lower_bound": "1_037", "upper_bound": "1_050"}}}, {"Rank": "Diamond III", "Players": "39_219", "Player_Percentage": "3.36", "Divisions": {"Division I": {"lower_bound": "935", "upper_bound": "938"}, "Division II": {"lower_bound": "940", "upper_bound": "957"}, "Division III": {"lower_bound": "958", "upper_bound": "973"}, "Division IV": {"lower_bound": "977", "upper_bound": "993"}}}, {"Rank": "Diamond II", "Players": "63_298", "Player_Percentage": "5.42", "Divisions": {"Division I": {"lower_bound": "875", "upper_bound": "878"}, "Division II": {"lower_bound": "880", "upper_bound": "893"}, "Division III": {"lower_bound": "898", "upper_bound": "909"}, "Division IV": {"lower_bound": "917", "upper_bound": "931"}}}, {"Rank": "Diamond I", "Players": "98_616", "Player_Percentage": "8.45", "Divisions": {"Division I": {"lower_bound": "815", "upper_bound": "818"}, "Division II": {"lower_bound": "820", "upper_bound": "837"}, "Division III": {"lower_bound": "838", "upper_bound": "855"}, "Division IV": {"lower_bound": "857", "upper_bound": "874"}}}, {"Rank": "Platinum III", "Players": "136_851", "Player_Percentage": "11.73", "Divisions": {"Division I": {"lower_bound": "755", "upper_bound": "758"}, "Division II": {"lower_bound": "759", "upper_bound": "777"}, "Division III": {"lower_bound": "778", "upper_bound": "793"}, "Division IV": {"lower_bound": "797", "upper_bound": "810"}}}, {"Rank": "Platinum II", "Players": "162_222", "Player_Percentage": "13.90", "Divisions": {"Division I": {"lower_bound": "695", "upper_bound": "698"}, "Division II": {"lower_bound": "699", "upper_bound": "717"}, "Division III": {"lower_bound": "718", "upper_bound": "735"}, "Division IV": {"lower_bound": "737", "upper_bound": "754"}}}, {"Rank": "Platinum I", "Players": "166_646", "Player_Percentage": "14.28", "Divisions": {"Division I": {"lower_bound": "635", "upper_bound": "638"}, "Division II": {"lower_bound": "639", "upper_bound": "657"}, "Division III": {"lower_bound": "658", "upper_bound": "676"}, "Division IV": {"lower_bound": "677", "upper_bound": "694"}}}, {"Rank": "Gold III", "Players": "131_022", "Player_Percentage": "11.23", "Divisions": {"Division I": {"lower_bound": "575", "upper_bound": "578"}, "Division II": {"lower_bound": "580", "upper_bound": "597"}, "Division III": {"lower_bound": "598", "upper_bound": "615"}, "Division IV": {"lower_bound": "617", "upper_bound": "634"}}}, {"Rank": "Gold II", "Players": "92_427", "Player_Percentage": "7.92", "Divisions": {"Division I": {"lower_bound": "515", "upper_bound": "518"}, "Division II": {"lower_bound": "520", "upper_bound": "537"}, "Division III": {"lower_bound": "538", "upper_bound": "556"}, "Division IV": {"lower_bound": "557", "upper_bound": "574"}}}, {"Rank": "Gold I", "Players": "56_654", "Player_Percentage": "4.85", "Divisions": {"Division I": {"lower_bound": "455", "upper_bound": "458"}, "Division II": {"lower_bound": "460", "upper_bound": "477"}, "Division III": {"lower_bound": "478", "upper_bound": "495"}, "Division IV": {"lower_bound": "497", "upper_bound": "514"}}}, {"Rank": "Silver III", "Players": "29_468", "Player_Percentage": "2.52", "Divisions": {"Division I": {"lower_bound": "395", "upper_bound": "398"}, "Division II": {"lower_bound": "400", "upper_bound": "417"}, "Division III": {"lower_bound": "423", "upper_bound": "435"}, "Division IV": {"lower_bound": "437", "upper_bound": "454"}}}, {"Rank": "Silver II", "Players": "14_517", "Player_Percentage": "1.24", "Divisions": {"Division I": {"lower_bound": "335", "upper_bound": "338"}, "Division II": {"lower_bound": "344", "upper_bound": "357"}, "Division III": {"lower_bound": "364", "upper_bound": "375"}, "Division IV": {"lower_bound": "377", "upper_bound": "394"}}}, {"Rank": "Silver I", "Players": "6_357", "Player_Percentage": "0.54", "Divisions": {"Division I": {"lower_bound": "275", "upper_bound": "278"}, "Division II": {"lower_bound": "280", "upper_bound": "297"}, "Division III": {"lower_bound": "301", "upper_bound": "315"}, "Division IV": {"lower_bound": "317", "upper_bound": "334"}}}, {"Rank": "Bronze III", "Players": "2_617", "Player_Percentage": "0.22", "Divisions": {"Division I": {"lower_bound": "215", "upper_bound": "218"}, "Division II": {"lower_bound": "221", "upper_bound": "237"}, "Division III": {"lower_bound": "240", "upper_bound": "255"}, "Division IV": {"lower_bound": "263", "upper_bound": "274"}}}, {"Rank": "Bronze II", "Players": "1_065", "Player_Percentage": "0.09", "Divisions": {"Division I": {"lower_bound": "155", "upper_bound": "158"}, "Division II": {"lower_bound": "164", "upper_bound": "177"}, "Division III": {"lower_bound": "183", "upper_bound": "195"}, "Division IV": {"lower_bound": "199", "upper_bound": "213"}}}, {"Rank": "Bronze I", "Players": "407", "Player_Percentage": "0.03", "Divisions": {"Division II": {"lower_bound": "126", "upper_bound": "126"}, "Division III": {"lower_bound": "129", "upper_bound": "134"}, "Division IV": {"lower_bound": "144", "upper_bound": "152"}}}, {"Rank": "Unranked", "Players": "120_375", "Player_Percentage": "10.31", "Divisions": {"Division I": {"lower_bound": "504", "upper_bound": "774"}}}]}}